{"assets":{"FD36A991230BAB93D976D6F66BFC96F3":{"type":"texture","index":70,"assetRequest":{"type":"slide","state":"outgoing","slide":"9A3F437D-300D-4E10-85E1-BEF1BC2BA6E2"},"url":{"web":"assets/FD36A991230BAB93D976D6F66BFC96F3.svg"},"width":1024,"height":768},"581299D91C38624757F6F66D266630C3":{"type":"texture","index":71,"assetRequest":{"type":"slide","state":"incoming","slide":"50A964CB-560D-489A-A070-3FAB9B098ED6"},"url":{"web":"assets/581299D91C38624757F6F66D266630C3.svg"},"width":1024,"height":768}},"events":[{"effects":[{"beginTime":0,"baseLayer":{"animations":[],"initialState":{"affineTransform":[1,0,0,1,0,0],"masksToBounds":false,"rotation":0,"scale":1,"position":{"pointX":512,"pointY":384},"width":1024,"sublayerTransform":[1,0,0,0,0,1,0,0,0,0,1,0,0,0,0,1],"contentsRect":{"y":0,"x":0,"width":1,"height":1},"opacity":1,"edgeAntialiasingMask":251658240,"height":768,"hidden":false,"anchorPoint":{"pointX":0.5,"pointY":0.5}},"objectID":"0","layers":[{"animations":[],"initialState":{"affineTransform":[1,0,0,1,0,0],"masksToBounds":false,"rotation":0,"scale":1,"position":{"pointX":512,"pointY":384},"width":1024,"sublayerTransform":[1,0,0,0,0,1,0,0,0,0,1,-0.0004922987690640373,0,0,0,1],"contentsRect":{"y":0,"x":0,"width":1,"height":1},"opacity":1,"edgeAntialiasingMask":251658240,"height":768,"hidden":false,"anchorPoint":{"pointX":0.5,"pointY":0.5}},"layers":[{"animations":[],"layers":[],"initialState":{"affineTransform":[1,0,0,1,0,0],"masksToBounds":false,"rotation":0,"scale":1,"position":{"pointX":512,"pointY":384},"width":1024,"sublayerTransform":[1,0,0,0,0,1,0,0,0,0,1,0,0,0,0,1],"contentsRect":{"y":0,"x":0,"width":1,"height":1},"opacity":1,"edgeAntialiasingMask":0,"height":768,"hidden":false,"anchorPoint":{"pointX":0.5,"pointY":0.5}},"texture":"581299D91C38624757F6F66D266630C3"},{"animations":[{"timeOffset":0,"from":{"scalar":false},"beginTime":0,"repeatCount":0,"fillMode":"both","property":"hidden","autoreverses":false,"duration":0.01,"to":{"scalar":true}}],"layers":[],"initialState":{"affineTransform":[1,0,0,1,0,0],"masksToBounds":false,"rotation":0,"scale":1,"position":{"pointX":512,"pointY":384},"width":1024,"sublayerTransform":[1,0,0,0,0,1,0,0,0,0,1,0,0,0,0,1],"contentsRect":{"y":0,"x":0,"width":1,"height":1},"opacity":1,"edgeAntialiasingMask":0,"height":768,"hidden":false,"anchorPoint":{"pointX":0.5,"pointY":0.5}},"texture":"FD36A991230BAB93D976D6F66BFC96F3"}]}]},"effects":[],"duration":0.01,"type":"transition","name":"none","objectID":"0"}],"automaticPlay":false,"hyperlinks":[],"accessibility":[{"text":"In summary","targetRectangle":{"y":316,"x":159.3333595693111,"width":707.4132807850838,"height":134.90234375}}],"baseLayer":{"animations":[],"initialState":{"affineTransform":[1,0,0,1,0,0],"masksToBounds":false,"rotation":0,"scale":1,"position":{"pointX":512,"pointY":384},"width":1024,"sublayerTransform":[1,0,0,0,0,1,0,0,0,0,1,0,0,0,0,1],"contentsRect":{"y":0,"x":0,"width":1,"height":1},"opacity":1,"edgeAntialiasingMask":251658240,"height":768,"hidden":false,"anchorPoint":{"pointX":0.5,"pointY":0.5}},"objectID":"0","layers":[{"animations":[],"initialState":{"affineTransform":[1,0,0,1,0,0],"masksToBounds":false,"rotation":0,"scale":1,"position":{"pointX":512,"pointY":384},"width":1024,"sublayerTransform":[1,0,0,0,0,1,0,0,0,0,1,-0.0004922987690640373,0,0,0,1],"contentsRect":{"y":0,"x":0,"width":1,"height":1},"opacity":1,"edgeAntialiasingMask":251658240,"height":768,"hidden":false,"anchorPoint":{"pointX":0.5,"pointY":0.5}},"layers":[{"animations":[],"layers":[],"initialState":{"affineTransform":[1,0,0,1,0,0],"masksToBounds":false,"rotation":0,"scale":1,"position":{"pointX":512,"pointY":384},"width":1024,"sublayerTransform":[1,0,0,0,0,1,0,0,0,0,1,0,0,0,0,1],"contentsRect":{"y":0,"x":0,"width":1,"height":1},"opacity":1,"edgeAntialiasingMask":0,"height":768,"hidden":false,"anchorPoint":{"pointX":0.5,"pointY":0.5}},"texture":"FD36A991230BAB93D976D6F66BFC96F3"}]}]}}]}